novita/__init__.py
novita/client.py
novita/exceptions.py
novita/py.typed
novita/api/__init__.py
novita/api/gpu.py
novita/api/resources/gpu/__init__.py
novita/api/resources/gpu/base.py
novita/api/resources/gpu/clusters.py
novita/api/resources/gpu/endpoints.py
novita/api/resources/gpu/image_prewarm.py
novita/api/resources/gpu/instances.py
novita/api/resources/gpu/jobs.py
novita/api/resources/gpu/metrics.py
novita/api/resources/gpu/networks.py
novita/api/resources/gpu/products.py
novita/api/resources/gpu/registries.py
novita/api/resources/gpu/storages.py
novita/api/resources/gpu/templates.py
novita/generated/__init__.py
novita/generated/models.py
novita_sdk-0.5.0.dist-info/licenses/LICENSE
novita_sdk-0.5.0.dist-info/METADATA
novita_sdk-0.5.0.dist-info/WHEEL
novita_sdk-0.5.0.dist-info/top_level.txt
novita_sdk-0.5.0.dist-info/RECORD
