Metadata-Version: 2.4
Name: novita-sdk
Version: 0.5.0
Summary: (Unofficial) Modern Python SDK for the Novita AI API
Author-email: Ronny Unger <phpworkx@gmail.com>
License-Expression: MIT
Project-URL: Homepage, https://github.com/php-workx/novita-sdk-python
Project-URL: Documentation, https://novita.ai/docs/api-reference/
Project-URL: Repository, https://github.com/php-workx/novita-sdk-python
Project-URL: Issues, https://github.com/php-workx/novita-sdk-python/issues
Keywords: novita,ai,api,sdk,machine-learning,gpu-cloud
Classifier: Development Status :: 4 - Beta
Classifier: Intended Audience :: Developers
Classifier: Programming Language :: Python :: 3
Classifier: Programming Language :: Python :: 3.11
Classifier: Programming Language :: Python :: 3.12
Classifier: Programming Language :: Python :: 3.13
Classifier: Typing :: Typed
Requires-Python: >=3.11
License-File: LICENSE
Requires-Dist: pydantic>=2.0.0
Requires-Dist: httpx>=0.27.0
Provides-Extra: dev
Requires-Dist: ruff==0.8.4; extra == "dev"
Requires-Dist: pytest>=7.4.0; extra == "dev"
Requires-Dist: pytest-httpx>=0.27.0; extra == "dev"
Requires-Dist: pytest-asyncio>=0.23.0; extra == "dev"
Requires-Dist: mypy>=1.7.0; extra == "dev"
Requires-Dist: pytest-cov>=4.1.0; extra == "dev"
Requires-Dist: datamodel-code-generator>=0.25.0; extra == "dev"
Requires-Dist: openapi-spec-validator>=0.7.0; extra == "dev"
Dynamic: license-file
